eric/__init__.py
eric/__main__.py
eric/colors.py
eric/core.py
eric/parser.py
eric/slide.py
eric_slides_neeraj-2.0.4.dist-info/METADATA
eric_slides_neeraj-2.0.4.dist-info/WHEEL
eric_slides_neeraj-2.0.4.dist-info/entry_points.txt
eric_slides_neeraj-2.0.4.dist-info/top_level.txt
eric_slides_neeraj-2.0.4.dist-info/RECORD
