Metadata-Version: 2.4
Name: eric-slides-neeraj
Version: 2.0.4
Summary: A terminal-based presentation tool with syntax highlighting
Author: Neeraj Narwariya
Requires-Python: >=3.6
Dynamic: author
Dynamic: requires-python
Dynamic: summary
